agm_io_utils/__init__.py
agm_io_utils/io_utils.py
agm_io_utils-0.0.6.dist-info/LICENSE
agm_io_utils-0.0.6.dist-info/METADATA
agm_io_utils-0.0.6.dist-info/WHEEL
agm_io_utils-0.0.6.dist-info/top_level.txt
agm_io_utils-0.0.6.dist-info/RECORD
