Metadata-Version: 2.1
Name: agm-io-utils
Version: 0.0.6
Summary: Offers special IO functions such as the recursive creation of a list of files in a folder, taking into account file extensions or properties.
Home-page: https://github.com/auximalia/agm_io_utils
Author: auximalia
Author-email: agm_io_utils@bureau-agamemnon.de
License: UNKNOWN
Platform: UNKNOWN
Classifier: Programming Language :: Python :: 3
Classifier: License :: OSI Approved :: MIT License
Classifier: Operating System :: OS Independent
Requires-Python: >=3.7
License-File: LICENSE
